{
  "applications": "*",
  "changelogDate": "20220107134243",
  "dto": "no",
  "embedded": false,
  "entityTableName": "ligne_cmd_client",
  "fields": [
    {
      "fieldName": "cmdQnCl",
      "fieldType": "Integer"
    },
    {
      "fieldName": "cmdNmPiecesCl",
      "fieldType": "Integer"
    }
  ],
  "fluentMethods": true,
  "jpaMetamodelFiltering": false,
  "name": "LigneCmdClient",
  "pagination": "no",
  "readOnly": false,
  "relationships": [
    {
      "otherEntityName": "article",
      "otherEntityRelationshipName": "ligneCmdClient",
      "relationshipName": "article",
      "relationshipType": "one-to-many"
    },
    {
      "otherEntityName": "commandeClient",
      "otherEntityRelationshipName": "ligneCmdClient",
      "relationshipName": "commandeClient",
      "relationshipType": "many-to-one"
    }
  ],
  "service": "serviceImpl"
}
